tpblite/__init__.py
tpblite/tpblite.py
tpblite/models/__init__.py
tpblite/models/constants.py
tpblite/models/torrents.py
tpblite/models/utils.py
tpblite-0.8.0.dist-info/LICENSE
tpblite-0.8.0.dist-info/METADATA
tpblite-0.8.0.dist-info/WHEEL
tpblite-0.8.0.dist-info/top_level.txt
tpblite-0.8.0.dist-info/RECORD
