Metadata-Version: 2.1
Name: tpblite
Version: 0.8.0
Summary: The Unofficial Pirate Bay Lightweight Python API
Home-page: https://github.com/mattlyon93/tpb-lite
Author: Matt Lyon
Author-email: matthewlyon18@gmail.com
License: MIT License
Download-URL: https://github.com/mattlyon93/tpb-lite/archive/v0.8.0.tar.gz
Keywords: ThePirateBay,PirateBay,torrent
Platform: UNKNOWN
Classifier: Development Status :: 3 - Alpha
Classifier: Programming Language :: Python
Classifier: Operating System :: Unix
Classifier: Operating System :: MacOS
Classifier: Topic :: Internet :: WWW/HTTP :: Browsers
Classifier: Topic :: Internet :: WWW/HTTP :: Indexing/Search
Classifier: Topic :: Utilities
Requires-Python: >=3.6
